micropython_icp10111/__init__.py
micropython_icp10111/icp10111.py
micropython_icp10111-0.1.0.dist-info/LICENSE
micropython_icp10111-0.1.0.dist-info/METADATA
micropython_icp10111-0.1.0.dist-info/WHEEL
micropython_icp10111-0.1.0.dist-info/top_level.txt
micropython_icp10111-0.1.0.dist-info/RECORD
