Metadata-Version: 2.1
Name: micropython-icp10111
Version: 0.1.0
Summary: MicroPython Driver for the TDK Barometric Pressure
Author-email: JDM <xxyx@mailmeto.mozmail.com>
License: MIT
Project-URL: Homepage, https://github.com/jposada202020/MicroPython_ICP10111
Keywords: sensor,micropython,icp10111,and,Temperature,Sensorpressure,barometric,micropython,temperature,tdk,icp-10111
Classifier: Intended Audience :: Developers
Classifier: Topic :: Software Development :: Libraries
Classifier: Topic :: Software Development :: Embedded Systems
Classifier: Topic :: System :: Hardware
Classifier: License :: OSI Approved :: MIT License
Classifier: Programming Language :: Python :: Implementation :: MicroPython
License-File: LICENSE
